windows_tools.wmi_queries-1.0.1-py3.12-nspkg.pth
windows_tools/wmi_queries/__init__.py
windows_tools.wmi_queries-1.0.1.dist-info/LICENSE
windows_tools.wmi_queries-1.0.1.dist-info/METADATA
windows_tools.wmi_queries-1.0.1.dist-info/WHEEL
windows_tools.wmi_queries-1.0.1.dist-info/namespace_packages.txt
windows_tools.wmi_queries-1.0.1.dist-info/top_level.txt
windows_tools.wmi_queries-1.0.1.dist-info/RECORD
